TimePoints/Measure.py
TimePoints/__init__.py
TimePoints-1.0.0.dist-info/LICENSE
TimePoints-1.0.0.dist-info/METADATA
TimePoints-1.0.0.dist-info/WHEEL
TimePoints-1.0.0.dist-info/top_level.txt
TimePoints-1.0.0.dist-info/RECORD
