Metadata-Version: 2.1
Name: TimePoints
Version: 1.0.0
Summary: Easily measure durations between time points in a code
Home-page: https://github.com/htarnacki/TimePoints
Author: Hubert Tarnacki
Author-email: hubert.tarnacki@gmail.com
License: MIT
Project-URL: Code, https://github.com/htarnacki/TimePoints
Project-URL: Issue tracker, https://github.com/htarnacki/TimePoints/issues
Keywords: time,duration,time points,measure,debug
Platform: UNKNOWN
Classifier: Intended Audience :: Developers
Classifier: License :: OSI Approved :: MIT License
Classifier: Programming Language :: Python
Classifier: Programming Language :: Python :: 3.7
Classifier: Topic :: System :: Monitoring
Classifier: Topic :: System :: Logging
Classifier: Topic :: Software Development :: Debuggers
Requires-Python: >=3.7.0
Provides-Extra: reports
Requires-Dist: rich ; extra == 'reports'
